[{"song_name":"DtMF","song_id":"3sK8wGT43QFpWrvNQsrQya","artist_name":"Bad Bunny","album_art":"https://i.scdn.co/image/ab67616d0000b273bbd45c8d36e0e045ef640411","track_duration":237117,"popularity":100,"release_date":"2025-01-05"},{"song_name":"BAILE INoLVIDABLE","song_id":"2lTm559tuIvatlT1u0JYG2","artist_name":"Bad Bunny","album_art":"https://i.scdn.co/image/ab67616d0000b273bbd45c8d36e0e045ef640411","track_duration":367725,"popularity":98,"release_date":"2025-01-05"},{"song_name":"Man I Need","song_id":"1qbmS6ep2hbBRaEZFpn7BX","artist_name":"Olivia Dean","album_art":"https://i.scdn.co/image/ab67616d0000b273e3d69e17dde129037a1f09e2","track_duration":184000,"popularity":97,"release_date":"2025-08-15"},{"song_name":"Choosin' Texas","song_id":"65DbTqJKhbwqYbZ1Okr0rc","artist_name":"Ella Langley","album_art":"https://i.scdn.co/image/ab67616d0000b27390958927fbba47a62c3e63f8","track_duration":232226,"popularity":90,"release_date":"2025-10-17"},{"song_name":"NUEVAYoL","song_id":"5TFD2bmFKGhoCRbX61nXY5","artist_name":"Bad Bunny","album_art":"https://i.scdn.co/image/ab67616d0000b273bbd45c8d36e0e045ef640411","track_duration":183685,"popularity":97,"release_date":"2025-01-05"},{"song_name":"Ordinary","song_id":"6qqrTXSdwiJaq8SO0X2lSe","artist_name":"Alex Warren","album_art":"https://i.scdn.co/image/ab67616d0000b273457cfd5a54720ab3b0820064","track_duration":186964,"popularity":89,"release_date":"2025-02-07"},{"song_name":"Tití Me Preguntó","song_id":"1IHWl5LamUGEuP4ozKQSXZ","artist_name":"Bad Bunny","album_art":"https://i.scdn.co/image/ab67616d0000b27349d694203245f241a1bcaa72","track_duration":243716,"popularity":94,"release_date":"2022-05-06"},{"song_name":"Opalite","song_id":"3yWuTOYDztXjZxdE2cIRUa","artist_name":"Taylor Swift","album_art":"https://i.scdn.co/image/ab67616d0000b273d7812467811a7da6e6a44902","track_duration":235355,"popularity":92,"release_date":"2025-10-03"},{"song_name":"Golden","song_id":"1CPZ5BxNNd0n0nF4Orb9JS","artist_name":"KPop Demon Hunters Cast","album_art":"https://i.scdn.co/image/ab67616d0000b2734dcb6c5df15cf74596ab25a4","track_duration":194607,"popularity":95,"release_date":"2025-06-20"},{"song_name":"I Just Might","song_id":"12bYYQaLqHliSXvRIYlq8G","artist_name":"Bruno Mars","album_art":"https://i.scdn.co/image/ab67616d0000b273e7623a0a60f330ee2b24d498","track_duration":212973,"popularity":94,"release_date":"2026-01-09"},{"song_name":"EoO","song_id":"6J5kc12BW5HuP3d7C3vvx8","artist_name":"Bad Bunny","album_art":"https://i.scdn.co/image/ab67616d0000b273bbd45c8d36e0e045ef640411","track_duration":204768,"popularity":95,"release_date":"2025-01-05"},{"song_name":"The Fate of Ophelia","song_id":"53iuhJlwXhSER5J2IYYv1W","artist_name":"Taylor Swift","album_art":"https://i.scdn.co/image/ab67616d0000b273d7812467811a7da6e6a44902","track_duration":226073,"popularity":97,"release_date":"2025-10-03"},{"song_name":"back to friends","song_id":"0FTmksd2dxiE5e3rWyJXs6","artist_name":"sombr","album_art":"https://i.scdn.co/image/ab67616d0000b2737fd4049ad3b037358cf809ef","track_duration":199032,"popularity":91,"release_date":"2024-12-27"},{"song_name":"VOY A LLeVARTE PA PR","song_id":"59D4DOkspUbWyMmbAPQkxZ","artist_name":"Bad Bunny","album_art":"https://i.scdn.co/image/ab67616d0000b273bbd45c8d36e0e045ef640411","track_duration":156364,"popularity":94,"release_date":"2025-01-05"},{"song_name":"Folded","song_id":"0bxPRWprUVpQK0UFcddkrA","artist_name":"Kehlani","album_art":"https://i.scdn.co/image/ab67616d0000b273ce5bc87f637b46ad01831fc4","track_duration":238120,"popularity":89,"release_date":"2025-06-11"},{"song_name":"Two Six","song_id":"57ENogEkvFsU7Wmt3lvQMG","artist_name":"J. Cole","album_art":"https://i.scdn.co/image/ab67616d0000b27380788f104c780412212e97e3","track_duration":196080,"popularity":83,"release_date":"2026-02-06"},{"song_name":"So Easy (To Fall In Love)","song_id":"6sGIMrtIzQjdzNndVxe397","artist_name":"Olivia Dean","album_art":"https://i.scdn.co/image/ab67616d0000b2739a336bfb6d40bbd90a507417","track_duration":169000,"popularity":96,"release_date":"2025-09-26"},{"song_name":"The Great Divide","song_id":"77zqs8ucHCSk5jh9TYec4b","artist_name":"Noah Kahan","album_art":"https://i.scdn.co/image/ab67616d0000b273a47374027a9f559917ba66ba","track_duration":317961,"popularity":88,"release_date":"2026-01-30"},{"song_name":"YUKON","song_id":"29iva9idM6rFCPUlu7Rhxl","artist_name":"Justin Bieber","album_art":"https://i.scdn.co/image/ab67616d0000b273d65c4773bc5061fd27facc5b","track_duration":163866,"popularity":85,"release_date":"2025-07-11"},{"song_name":"WHERE IS MY HUSBAND!","song_id":"55lijDD6OAjLFFUHU9tcDm","artist_name":"RAYE","album_art":"https://i.scdn.co/image/ab67616d0000b2737cc8cee5c81409833e540974","track_duration":196795,"popularity":96,"release_date":"2025-09-19"},{"song_name":"E85","song_id":"3B4cjvGlPvyBLNG3AzEgkZ","artist_name":"Don Toliver","album_art":"https://i.scdn.co/image/ab67616d0000b27325c28f3c9fbdbab1a88dd619","track_duration":153181,"popularity":87,"release_date":"2026-01-30"},{"song_name":"Body","song_id":"0FlcmZ13DGRmscCroro9GO","artist_name":"Don Toliver","album_art":"https://i.scdn.co/image/ab67616d0000b27325c28f3c9fbdbab1a88dd619","track_duration":155753,"popularity":88,"release_date":"2026-01-30"},{"song_name":"End of Beginning","song_id":"3qhlB30KknSejmIvZZLjOD","artist_name":"Djo","album_art":"https://i.scdn.co/image/ab67616d0000b273fddfffec51b4580acae727c1","track_duration":159245,"popularity":99,"release_date":"2022-09-16"},{"song_name":"Aperture","song_id":"45Z3m6yazmAi4jZuW0tzW0","artist_name":"Harry Styles","album_art":"https://i.scdn.co/image/ab67616d0000b2736b10b937d94f055f8890cb62","track_duration":311733,"popularity":92,"release_date":"2026-01-22"},{"song_name":"20 Cigarettes","song_id":"0YsIYFRoxkmEvbKCwTp0Tg","artist_name":"Morgan Wallen","album_art":"https://i.scdn.co/image/ab67616d0000b27335ea219ce47813b5e2dc3745","track_duration":160901,"popularity":79,"release_date":"2025-05-16"},{"song_name":"What You Saying","song_id":"7cjoZVmWe2xsGR4wcXiV2v","artist_name":"Lil Uzi Vert","album_art":"https://i.scdn.co/image/ab67616d0000b27338b6341d4c2a56836a650165","track_duration":131729,"popularity":91,"release_date":"2025-12-22"},{"song_name":"LA CANCIÓN","song_id":"0fea68AdmYNygeTGI4RC18","artist_name":"J Balvin","album_art":"https://i.scdn.co/image/ab67616d0000b2734891d9b25d8919448388f3bb","track_duration":242573,"popularity":92,"release_date":"2019-06-28"},{"song_name":"Sleepless in a Hotel Room","song_id":"2za9t2qpWyUpIhnJcwopPt","artist_name":"Luke Combs","album_art":"https://i.scdn.co/image/ab67616d0000b2731040d6c19f908bda1fb5948b","track_duration":177674,"popularity":84,"release_date":"2026-01-07"},{"song_name":"SAFETY","song_id":"3sJLoIc9y1b4gKAP8ZNsR9","artist_name":"J. Cole","album_art":"https://i.scdn.co/image/ab67616d0000b27380788f104c780412212e97e3","track_duration":318066,"popularity":81,"release_date":"2026-02-06"},{"song_name":"Poor Thang","song_id":"1nhNz1tWU8p5WvFAAgFW2h","artist_name":"J. Cole","album_art":"https://i.scdn.co/image/ab67616d0000b27380788f104c780412212e97e3","track_duration":290346,"popularity":80,"release_date":"2026-02-06"},{"song_name":"Homewrecker","song_id":"7tICCrK3CcyRFKza7yrR0z","artist_name":"sombr","album_art":"https://i.scdn.co/image/ab67616d0000b2739a8d41dca4c7d0ef23d76dd7","track_duration":209066,"popularity":88,"release_date":"2026-02-05"},{"song_name":"WHO TF IZ U","song_id":"5ZfOg71oANMaKmswvSEF2r","artist_name":"J. Cole","album_art":"https://i.scdn.co/image/ab67616d0000b27380788f104c780412212e97e3","track_duration":277013,"popularity":79,"release_date":"2026-02-06"},{"song_name":"Run A Train (with Future)","song_id":"4pPJQ2p8jIsBuvxEIW2R99","artist_name":"J. Cole","album_art":"https://i.scdn.co/image/ab67616d0000b27380788f104c780412212e97e3","track_duration":242573,"popularity":80,"release_date":"2026-02-06"},{"song_name":"Bunce Road Blues (with Future & Tems)","song_id":"6jtqO14L18plBtpDTtUkFR","artist_name":"J. Cole","album_art":"https://i.scdn.co/image/ab67616d0000b27380788f104c780412212e97e3","track_duration":310626,"popularity":81,"release_date":"2026-02-06"},{"song_name":"Die On This Hill","song_id":"2gYTC8DsplN3RNdpdBcCOQ","artist_name":"SIENNA SPIRO","album_art":"https://i.scdn.co/image/ab67616d0000b273ec4833919808083d733ca9af","track_duration":217008,"popularity":94,"release_date":"2025-10-10"},{"song_name":"Legacy (with PJ)","song_id":"7oSdhQFfq5ScVjRkVcj4Ua","artist_name":"J. Cole","album_art":"https://i.scdn.co/image/ab67616d0000b27380788f104c780412212e97e3","track_duration":235906,"popularity":79,"release_date":"2026-02-06"},{"song_name":"MONACO","song_id":"4MjDJD8cW7iVeWInc2Bdyj","artist_name":"Bad Bunny","album_art":"https://i.scdn.co/image/ab67616d0000b2732ea1f035463d11e1fc3b193d","track_duration":267194,"popularity":88,"release_date":"2023-10-13"},{"song_name":"TIT FOR TAT","song_id":"04a44cx2PJthIbN2aLMXhl","artist_name":"Tate McRae","album_art":"https://i.scdn.co/image/ab67616d0000b273d0401a5b4ca2a799cd599abf","track_duration":177208,"popularity":80,"release_date":"2025-09-26"},{"song_name":"VeLDÁ","song_id":"7d6yK8v8J484SWH5prIQiE","artist_name":"Bad Bunny","album_art":"https://i.scdn.co/image/ab67616d0000b273bbd45c8d36e0e045ef640411","track_duration":235336,"popularity":92,"release_date":"2025-01-05"},{"song_name":"A Couple Minutes","song_id":"312z6PZ8wwREck8613PkJk","artist_name":"Olivia Dean","album_art":"https://i.scdn.co/image/ab67616d0000b2739a336bfb6d40bbd90a507417","track_duration":212000,"popularity":89,"release_date":"2025-09-26"},{"song_name":"Amen","song_id":"3Q5b9lTrxvv6f8jLX4M6VJ","artist_name":"Shaboozey","album_art":"https://i.scdn.co/image/ab67616d0000b27322c5399d1120f2ef71852303","track_duration":197403,"popularity":59,"release_date":"2025-04-24"},{"song_name":"Better Me For You (Brown Eyes)","song_id":"4Iu73sdCNxZXZUIyClMoPZ","artist_name":"Max McNown","album_art":"https://i.scdn.co/image/ab67616d0000b2730eb26fce888d263b2cdf5614","track_duration":194120,"popularity":81,"release_date":"2025-01-24"},{"song_name":"The Let Out","song_id":"2aNaJLXE4SXbm9L23qpHTG","artist_name":"J. Cole","album_art":"https://i.scdn.co/image/ab67616d0000b27380788f104c780412212e97e3","track_duration":254013,"popularity":79,"release_date":"2026-02-06"},{"song_name":"It Depends (feat. Bryson Tiller)","song_id":"0t3pcqgBjuAVBgY2oEUIlH","artist_name":"Chris Brown","album_art":"https://i.scdn.co/image/ab67616d0000b2733f3e9b76bb402edc64b2ed6b","track_duration":271875,"popularity":76,"release_date":"2025-07-25"},{"song_name":"Dracula","song_id":"709ZIqPHyFOpx2QdjmeWAM","artist_name":"Tame Impala","album_art":"https://i.scdn.co/image/ab67616d0000b2734806a1c10aa685b1b936158b","track_duration":205308,"popularity":82,"release_date":"2025-09-26"},{"song_name":"Drum n Bass","song_id":"290Vqn3zZX5QarUQra9LT2","artist_name":"J. Cole","album_art":"https://i.scdn.co/image/ab67616d0000b27380788f104c780412212e97e3","track_duration":254973,"popularity":78,"release_date":"2026-02-06"},{"song_name":"Qué Pasaría...","song_id":"0OxKf18dUo2G5dFOQYCvBN","artist_name":"Rauw Alejandro","album_art":"https://i.scdn.co/image/ab67616d0000b273d9cb889a8d0a6dd1007385ba","track_duration":191018,"popularity":71,"release_date":"2024-11-14"},{"song_name":"DÁKITI","song_id":"47EiUVwUp4C9fGccaPuUCS","artist_name":"Bad Bunny","album_art":"https://i.scdn.co/image/ab67616d0000b27334c8199b0b3b3fb42b8a98a8","track_duration":205090,"popularity":82,"release_date":"2020-10-30"},{"song_name":"The Fall","song_id":"4QpuZ1Qbcd11aOtY1kGMRg","artist_name":"Cody Johnson","album_art":"https://i.scdn.co/image/ab67616d0000b273240b20760030862b1697b25a","track_duration":197626,"popularity":78,"release_date":"2024-11-01"},{"song_name":"LET 'EM KNOW","song_id":"6AXf9n3qazR1bE1dngnqxi","artist_name":"T.I.","album_art":"https://i.scdn.co/image/ab67616d0000b2734b4019f6b27b37d6b47af6b9","track_duration":179924,"popularity":76,"release_date":"2026-01-18"},{"song_name":"Stateside + Zara Larsson","song_id":"1DwscornXpj8fmOmYVlqZt","artist_name":"PinkPantheress","album_art":"https://i.scdn.co/image/ab67616d0000b273684ecc5bc1b724d0106ad694","track_duration":184761,"popularity":91,"release_date":"2025-10-10"},{"song_name":"Bombs in the Ville/Hit the Gas","song_id":"0Awr3NZMkRHQFabkMxW1VT","artist_name":"J. Cole","album_art":"https://i.scdn.co/image/ab67616d0000b27380788f104c780412212e97e3","track_duration":246440,"popularity":78,"release_date":"2026-02-06"},{"song_name":"29 Intro","song_id":"0EqH5Wz93cJtfUGv3vtQPY","artist_name":"J. Cole","album_art":"https://i.scdn.co/image/ab67616d0000b27380788f104c780412212e97e3","track_duration":57733,"popularity":76,"release_date":"2026-02-06"},{"song_name":"Secondhand (feat. Rema)","song_id":"4Z5KKoBGxpJo8YbDcGQXd5","artist_name":"Don Toliver","album_art":"https://i.scdn.co/image/ab67616d0000b27325c28f3c9fbdbab1a88dd619","track_duration":226666,"popularity":86,"release_date":"2026-01-30"},{"song_name":"ATM","song_id":"0FrESd7LNffZyGZ37VuSmH","artist_name":"Don Toliver","album_art":"https://i.scdn.co/image/ab67616d0000b273df7b08323837d5d0558ad460","track_duration":180705,"popularity":78,"release_date":"2026-01-23"},{"song_name":"Hell At Night (feat. Ella Langley)","song_id":"0U1nO2frLx8w2dIsfvlP1d","artist_name":"BigXthaPlug","album_art":"https://i.scdn.co/image/ab67616d0000b273911cda459bd531ddc3888236","track_duration":179240,"popularity":74,"release_date":"2025-08-08"},{"song_name":"Days Like These","song_id":"5E2y5TSb2RJNCO01QjkgLf","artist_name":"Luke Combs","album_art":"https://i.scdn.co/image/ab67616d0000b27398d0214b1742dbf61de5888e","track_duration":221711,"popularity":71,"release_date":"2025-10-03"},{"song_name":"How Far Does A Goodbye Go","song_id":"17U2M7HB14yGe9QSAmbyyB","artist_name":"Jason Aldean","album_art":"https://i.scdn.co/image/ab67616d0000b273205cbaa5da736e4465309a19","track_duration":235727,"popularity":67,"release_date":"2025-09-12"},{"song_name":"39 Intro","song_id":"4DvoYgOZXnqmKuc2GzzFHz","artist_name":"J. Cole","album_art":"https://i.scdn.co/image/ab67616d0000b27380788f104c780412212e97e3","track_duration":366413,"popularity":78,"release_date":"2026-02-06"},{"song_name":"CAFé CON RON","song_id":"6VNXmo59yDYgcwLS17UNAW","artist_name":"Bad Bunny","album_art":"https://i.scdn.co/image/ab67616d0000b273bbd45c8d36e0e045ef640411","track_duration":228836,"popularity":88,"release_date":"2025-01-05"},{"song_name":"12 to 12","song_id":"6MrLkXsMmHaYt680fhJUAq","artist_name":"sombr","album_art":"https://i.scdn.co/image/ab67616d0000b2736e3665d175bd9aadb15b08b2","track_duration":242903,"popularity":83,"release_date":"2025-07-24"},{"song_name":"Dandelion","song_id":"7FudQLDIYCX6F7ruexVn2X","artist_name":"Ella Langley","album_art":"https://i.scdn.co/image/ab67616d0000b2738c4aa8e46455efcaa08c4085","track_duration":240946,"popularity":79,"release_date":"2026-01-30"},{"song_name":"WELTiTA","song_id":"5WEF0icHWmAZBBMglBd599","artist_name":"Bad Bunny","album_art":"https://i.scdn.co/image/ab67616d0000b273bbd45c8d36e0e045ef640411","track_duration":187507,"popularity":89,"release_date":"2025-01-05"},{"song_name":"Old Dog (with Petey Pablo)","song_id":"6WGJ7hPYHXu3aQ6x8GzigX","artist_name":"J. Cole","album_art":"https://i.scdn.co/image/ab67616d0000b27380788f104c780412212e97e3","track_duration":202253,"popularity":77,"release_date":"2026-02-06"},{"song_name":"Lush Life","song_id":"1rIKgCH4H52lrvDcz50hS8","artist_name":"Zara Larsson","album_art":"https://i.scdn.co/image/ab67616d0000b273aa82525b9cca69ba27d385b7","track_duration":200646,"popularity":94,"release_date":"2017-03-17"},{"song_name":"LA MuDANZA","song_id":"3G7agPwWfcORnWCAGMDOpm","artist_name":"Bad Bunny","album_art":"https://i.scdn.co/image/ab67616d0000b273bbd45c8d36e0e045ef640411","track_duration":213010,"popularity":87,"release_date":"2025-01-05"},{"song_name":"PERFuMITO NUEVO","song_id":"1Q9Efnm5csdCMFynISxL2x","artist_name":"Bad Bunny","album_art":"https://i.scdn.co/image/ab67616d0000b273bbd45c8d36e0e045ef640411","track_duration":200680,"popularity":87,"release_date":"2025-01-05"},{"song_name":"The Fall-Off is Inevitable","song_id":"3kUHIvjJ8p9UzeaeeqHkfg","artist_name":"J. Cole","album_art":"https://i.scdn.co/image/ab67616d0000b27380788f104c780412212e97e3","track_duration":176253,"popularity":77,"release_date":"2026-02-06"},{"song_name":"'Til You Can't","song_id":"3zHKfwfp1i6aK6SYyGcXM0","artist_name":"Kid Rock","album_art":"https://i.scdn.co/image/ab67616d0000b273144c244515ecd2584bb0ee0f","track_duration":309482,"popularity":62,"release_date":"2026-02-09"},{"song_name":"Travelin' Soldier","song_id":"4ThbwJaIWVxXZ1qJaHQBCz","artist_name":"Cody Johnson","album_art":"https://i.scdn.co/image/ab67616d0000b273dd631f0e629677d200d00126","track_duration":255466,"popularity":79,"release_date":"2025-11-07"},{"song_name":"KLOuFRENS","song_id":"4MUrUT38U98olfnyzMBCzm","artist_name":"Bad Bunny","album_art":"https://i.scdn.co/image/ab67616d0000b273bbd45c8d36e0e045ef640411","track_duration":199114,"popularity":90,"release_date":"2025-01-05"},{"song_name":"The Villest (with Erykah Badu)","song_id":"1lYM9PgB0QOk3pDo8h0UiN","artist_name":"J. Cole","album_art":"https://i.scdn.co/image/ab67616d0000b27380788f104c780412212e97e3","track_duration":270626,"popularity":77,"release_date":"2026-02-06"},{"song_name":"Life Sentence","song_id":"0pchHye1t8VA9gTHK3hAAZ","artist_name":"J. Cole","album_art":"https://i.scdn.co/image/ab67616d0000b27380788f104c780412212e97e3","track_duration":252986,"popularity":77,"release_date":"2026-02-06"},{"song_name":"I Ain't Comin' Back (feat. Post Malone)","song_id":"1BDLD4c07q0bmq2VCRsXoE","artist_name":"Morgan Wallen","album_art":"https://i.scdn.co/image/ab67616d0000b27335ea219ce47813b5e2dc3745","track_duration":175271,"popularity":72,"release_date":"2025-05-16"},{"song_name":"Lonely at the Top (Bonus)","song_id":"3QQp1Y4zWok1YvzB4zutGy","artist_name":"J. Cole","album_art":"https://i.scdn.co/image/ab67616d0000b27380788f104c780412212e97e3","track_duration":204413,"popularity":76,"release_date":"2026-02-06"},{"song_name":"Rendezvous (feat. Yeat)","song_id":"2Ejyg4CavumEr7lFUkk9aF","artist_name":"Don Toliver","album_art":"https://i.scdn.co/image/ab67616d0000b27325c28f3c9fbdbab1a88dd619","track_duration":146801,"popularity":83,"release_date":"2026-01-30"},{"song_name":"McArthur","song_id":"6yOHshc12fwMtM74xoy4je","artist_name":"HARDY","album_art":"https://i.scdn.co/image/ab67616d0000b2733095a6008ce338cea3d13fff","track_duration":231533,"popularity":77,"release_date":"2026-01-30"},{"song_name":"Only You (with Burna Boy)","song_id":"0nn0Z1o1WI01pB7oEPiJeE","artist_name":"J. Cole","album_art":"https://i.scdn.co/image/ab67616d0000b27380788f104c780412212e97e3","track_duration":286866,"popularity":77,"release_date":"2026-02-06"},{"song_name":"Tiramisu","song_id":"2GHKo6nrSjruvBEQbzD7Fw","artist_name":"Don Toliver","album_art":"https://i.scdn.co/image/ab67616d0000b27325c28f3c9fbdbab1a88dd619","track_duration":138947,"popularity":81,"release_date":"2026-01-30"},{"song_name":"CHANEL","song_id":"4VxTzYm00mg82MuoT35Ja7","artist_name":"Tyla","album_art":"https://i.scdn.co/image/ab67616d0000b273c1cfff2e89a49729b648e56d","track_duration":188059,"popularity":91,"release_date":"2025-10-24"},{"song_name":"When Did You Get Hot?","song_id":"0je57Uq5eTk1wrPzn9sWbl","artist_name":"Sabrina Carpenter","album_art":"https://i.scdn.co/image/ab67616d0000b273b1863bf95557ea7f357c4947","track_duration":145398,"popularity":87,"release_date":"2025-08-29"},{"song_name":"Gemstone","song_id":"6d9Cs2D2RSIl9c0ulgnFe8","artist_name":"Don Toliver","album_art":"https://i.scdn.co/image/ab67616d0000b27325c28f3c9fbdbab1a88dd619","track_duration":121690,"popularity":82,"release_date":"2026-01-30"},{"song_name":"I Love Her Again","song_id":"5pjf75G1zn9EEFa8iaCV5h","artist_name":"J. Cole","album_art":"https://i.scdn.co/image/ab67616d0000b27380788f104c780412212e97e3","track_duration":332386,"popularity":77,"release_date":"2026-02-06"},{"song_name":"Call Back","song_id":"16yVaWo0Gmvs2wlnmJbcH7","artist_name":"Don Toliver","album_art":"https://i.scdn.co/image/ab67616d0000b27325c28f3c9fbdbab1a88dd619","track_duration":123840,"popularity":82,"release_date":"2026-01-30"},{"song_name":"Beautiful Things","song_id":"6WjwYL2tzzci2pvpv50rS4","artist_name":"Megan Moroney","album_art":"https://i.scdn.co/image/ab67616d0000b273d0783d5c3d7447542b352823","track_duration":235535,"popularity":70,"release_date":"2025-10-24"},{"song_name":"Excavator","song_id":"2A5cwtDZpk7RvsPolrF4UL","artist_name":"Don Toliver","album_art":"https://i.scdn.co/image/ab67616d0000b27325c28f3c9fbdbab1a88dd619","track_duration":211106,"popularity":81,"release_date":"2026-01-30"},{"song_name":"LO QUE LE PASÓ A HAWAii","song_id":"1Hg0e997pObvZ91w1FCPFk","artist_name":"Bad Bunny","album_art":"https://i.scdn.co/image/ab67616d0000b273bbd45c8d36e0e045ef640411","track_duration":229381,"popularity":85,"release_date":"2025-01-05"},{"song_name":"Gone Gone Gone","song_id":"3Dy4xsff7c0fRaTJpA54yd","artist_name":"David Guetta","album_art":"https://i.scdn.co/image/ab67616d0000b273b89fa8e4480031eb17c2bf4f","track_duration":198004,"popularity":83,"release_date":"2025-10-10"},{"song_name":"4 Raws","song_id":"554qQSs9lpRVq6TlaaiIKT","artist_name":"EsDeeKid","album_art":"https://i.scdn.co/image/ab67616d0000b273cff4bd68d5d0dd9a0a748045","track_duration":146666,"popularity":90,"release_date":"2025-06-20"},{"song_name":"Brunette","song_id":"21T9HvQ0KUWFDum6P1Qc7i","artist_name":"Tucker Wetmore","album_art":"https://i.scdn.co/image/ab67616d0000b2735cf183940a142a32c2276fb2","track_duration":139173,"popularity":78,"release_date":"2025-04-25"},{"song_name":"Midnight Sun","song_id":"37UCSVSqiPGdR1DijOFyYY","artist_name":"Zara Larsson","album_art":"https://i.scdn.co/image/ab67616d0000b27339905bfc6729b13ec7a7fead","track_duration":189898,"popularity":81,"release_date":"2025-06-13"},{"song_name":"EL CLúB","song_id":"0iKo4pNNjHHdKUcFARlfCa","artist_name":"Bad Bunny","album_art":"https://i.scdn.co/image/ab67616d0000b273bbd45c8d36e0e045ef640411","track_duration":222568,"popularity":85,"release_date":"2025-01-05"},{"song_name":"FDO","song_id":"5YbDA37CN0YcgZXF6L2cBX","artist_name":"Pooh Shiesty","album_art":"https://i.scdn.co/image/ab67616d0000b273dd064d13864cf1c599680eef","track_duration":319213,"popularity":78,"release_date":"2025-12-12"},{"song_name":"Say Why","song_id":"0BUvxX1tTOSJcsn6Y24Bsp","artist_name":"Zach Bryan","album_art":"https://i.scdn.co/image/ab67616d0000b2736addb951ebfd51d72b42123f","track_duration":143985,"popularity":81,"release_date":"2026-01-09"},{"song_name":"ErrTime","song_id":"2cBtsB7Pi89q9yWk59a2sX","artist_name":"Cardi B","album_art":"https://i.scdn.co/image/ab67616d0000b2734449c12628ef639dd6500c4a","track_duration":146560,"popularity":60,"release_date":"2025-09-19"},{"song_name":"Nice To Each Other","song_id":"7gKxCvTDWwV9wBhdeBbr3l","artist_name":"Olivia Dean","album_art":"https://i.scdn.co/image/ab67616d0000b273a9e75099d7065c71cc7ede72","track_duration":209000,"popularity":89,"release_date":"2025-05-30"},{"song_name":"Babydoll","song_id":"7yNf9YjeO5JXUE3JEBgnYc","artist_name":"Dominic Fike","album_art":"https://i.scdn.co/image/ab67616d0000b2737b1b6f41c1645af9757d5616","track_duration":97960,"popularity":89,"release_date":"2018-10-16"},{"song_name":"Rosary (feat. Travis Scott)","song_id":"4FUQtedaG22FWZ6lGyRApm","artist_name":"Don Toliver","album_art":"https://i.scdn.co/image/ab67616d0000b27325c28f3c9fbdbab1a88dd619","track_duration":194594,"popularity":82,"release_date":"2026-01-30"},{"song_name":"Man Up Above","song_id":"0C9B7SpULk3KlkOz3MhTEb","artist_name":"J. Cole","album_art":"https://i.scdn.co/image/ab67616d0000b27380788f104c780412212e97e3","track_duration":298360,"popularity":75,"release_date":"2026-02-06"},{"song_name":"Quik Stop","song_id":"050ECC7Yu78pTJP8PrMo8o","artist_name":"J. Cole","album_art":"https://i.scdn.co/image/ab67616d0000b27380788f104c780412212e97e3","track_duration":264520,"popularity":75,"release_date":"2026-02-06"}]
